setdb/__init__.py
SetDB-0.1.dist-info/METADATA
SetDB-0.1.dist-info/WHEEL
SetDB-0.1.dist-info/top_level.txt
SetDB-0.1.dist-info/RECORD
