Metadata-Version: 2.1
Name: SetDB
Version: 0.1
Summary: The simplest way to set up a Python database
Home-page: https://pypi.org/project/SetDB/
Author: Kayra Aça
Author-email: kayraaca@gmail.com
License: UNKNOWN
Platform: UNKNOWN
Classifier: Programming Language :: Python :: 3
Classifier: License :: OSI Approved :: MIT License
Requires-Python: >=3.7
